Metadata-Version: 2.1
Name: tee4py
Version: 0.2.0
Summary: tee4py is a python implementation the Unix tee command, allowing output to be written to the terminal and a file simultaneously.
Home-page: https://gitlab.com/RhydianL/tee4py
Author: Rhydian Lewis
Author-email: rhydian.lewis@swansea.ac.uk
License: UNKNOWN
Platform: UNKNOWN
Classifier: Programming Language :: Python :: 3
Classifier: License :: OSI Approved :: MIT License
Classifier: Operating System :: OS Independent
Requires-Python: >=3.6
